{"/":{"title":"Introduction","data":{"":"Empty"}},"/pl_playtime":{"title":"pl playtime","data":{"command#Command":"open shop: playtime\ngive coins: givecoins [playerid/citizenid] [amount] \ngive coins: removecoins [playerid/citizenid] [amount] \nset coins: setcoins [playerid/citizenid] [amount]","reward#Reward":"Config.Reward = {\n    -- ITEMS\n    { name = 'copper', label = 'Copper', quantity = 20, price = 10, originalPrice = 35, discount = '-20%', category = 'ITEMS' },\n    { name = 'lockpick', label = 'ADVANCED LOCKPICK', quantity = 5, price = 48, discount = '', category = 'ITEMS' },\n    { name = 'bandage', label = 'Bandage', quantity = 20, price = 20, originalPrice = 25, discount = '-20%', category = 'ITEMS' },\n    { name = 'armor', label = 'ARMOUR 10%', quantity = 1, price = 66, discount = '', category = 'ITEMS' },\n    { name = 'binoculars', label = 'Binoculars', quantity = 1, price = 96, discount = '', category = 'ITEMS' },\n    { name = 'firework1', label = 'Firework', quantity = 1, price = 66, originalPrice = 75, discount = '-20%', category = 'ITEMS' },\n    { name = 'radio', label = 'Radio', quantity = 1, price = 35, discount = '', category = 'ITEMS' },\n    { name = 'aluminum', label = 'Aluminum', quantity = 1, price = 10, originalPrice = 35, discount = '-40%', category = 'ITEMS' },\n    { name = 'cola', label = 'Coca-Cola', quantity = 1, price = 70, discount = '', category = 'ITEMS' },\n    -- VEHICLES\n    { name = 'zentorno', label = 'ZENTORNO', quantity = 1, price = 130, originalPrice = 160, discount = '-20%', category = 'VEHICLES' },\n    { name = 'kuruma2', label = 'KURUMA', quantity = 1, price = 170, discount = '', category = 'VEHICLES' },\n    { name = 'asbo', label = 'Asbo', quantity = 1, price = 160, originalPrice = 170, discount = '-20%', category = 'VEHICLES' },\n    { name = 'monstrociti', label = 'MonstroCiti', quantity = 1, price = 120, originalPrice = 150, discount = '-20%', category = 'VEHICLES' },\n    { name = 'bati2', label = 'Bati 801RR', quantity = 1, price = 100, discount = '', category = 'VEHICLES' },\n    -- WEAPONS\n    { name = 'weapon_pistol', label = 'PISTOL', quantity = 1, price = 50, discount = '', category = 'WEAPONS' },\n    { name = 'weapon_pistol50', label = 'PISTOL 50', quantity = 1, price = 60, originalPrice = 75, discount = '-20%', category = 'WEAPONS' },\n    -- Daily deals\n    { name = 'weapon_wrench', label = 'Wrench', quantity = 1, price = 40, originalPrice = 60, discount = '-33%', category = 'WEAPONS', isDailyDeal = true },\n    { name = 'ammo-50', label = '.50 AE', quantity = 1, price = 45, originalPrice = 60, discount = '-25%', category = 'ITEMS', isDailyDeal = true },\n    { name = 'weapon_switchblade', label = 'Switchblade', quantity = 1, price = 40, discount = '-20%', category = 'WEAPONS', isDailyDeal = true }    \n}","mission#Mission":"Config.Mission = {\n    {\n        id = 1, -- The ID must not be the same as the previous ID because the completed mission ID will be stored in the player database.\n        title = 'Kill 5 players',\n        description = 'You should kill 5 players. You are a killer now!',\n        reward = 5,\n        total = 5,\n    },\n    {\n        id = 2,\n        title = 'Mining Stone Collection 50 times',\n        description = 'Mining Stone Collection 50 times',\n        reward = 30,\n        total = 50,\n    },\n    {\n        id = 3,\n        title = 'Kill 10 players',\n        description = 'You should kill 10 players. You are a killer now!',\n        reward = 25,\n        total = 10,\n    },\n}","supported-frameworks#Supported Frameworks":"qb-core\nesx\nqbx_core"}},"/pl_playtime/Functions/Server":{"title":"Server","data":{"server-side#Server side":"exports['pl_playtime']:UpdateQuestProgress(source, questId, amount)"}},"/pl_playtime/Xample":{"title":"Xample","data":{"xampel#Xampel":"server.lua\n--/testquest <questId> [amount]\nRegisterCommand('testquest', function(source, args)\n    local questId = tonumber(args[1])\n    local amount = tonumber(args[2]) or 1\n    \n    if not questId then return end\n    \n    exports['pl_playtime']:UpdateQuestProgress(source, questId, amount)\n    \nend, false)"}}}